ms_auth/__init__.py
ms_auth/auth.py
ms_auth/ms_auth.so
ms_auth-1.1.6.dist-info/LICENSE
ms_auth-1.1.6.dist-info/METADATA
ms_auth-1.1.6.dist-info/WHEEL
ms_auth-1.1.6.dist-info/top_level.txt
ms_auth-1.1.6.dist-info/RECORD
